pydozer/__init__.py
pydozer/api.py
pydozer/auth.py
pydozer/auth_pb2.py
pydozer/auth_pb2_grpc.py
pydozer/common_pb2.py
pydozer/common_pb2_grpc.py
pydozer/health_pb2.py
pydozer/health_pb2_grpc.py
pydozer/helper.py
pydozer/ingest.py
pydozer/ingest_pb2.py
pydozer/ingest_pb2_grpc.py
pydozer/types_pb2.py
pydozer/types_pb2_grpc.py
pydozer-0.2.1.dist-info/LICENSE
pydozer-0.2.1.dist-info/METADATA
pydozer-0.2.1.dist-info/WHEEL
pydozer-0.2.1.dist-info/RECORD
