Metadata-Version: 2.1
Name: pydozer
Version: 0.2.1
Summary: Python wrapper for the Dozer API
License: Apache-2.0
Author: Dozer Team
Author-email: api@getdozer.io
Requires-Python: >=3.9,<4.0
Classifier: License :: OSI Approved :: Apache Software License
Classifier: Programming Language :: Python :: 3
Classifier: Programming Language :: Python :: 3.9
Classifier: Programming Language :: Python :: 3.10
Classifier: Programming Language :: Python :: 3.11
Requires-Dist: grpcio (>=1.51.3,<2.0.0)
Requires-Dist: grpcio-reflection (>=1.51.3,<2.0.0)
Requires-Dist: polars (>=0.16.10,<0.17.0)
Requires-Dist: protobuf (>=4.22.0,<5.0.0)
Requires-Dist: pyarrow (>=11.0.0,<12.0.0)
Requires-Dist: tqdm (>=4.65.0,<5.0.0)
